pyseek/__init__.py
pyseek/__main__.py
pyseek/config.py
pyseek/edgar.py
pyseek/errors.py
pyseek/models.py
pyseek/setup.py
pyseek/utils.py
pyseek-0.2.1.dist-info/entry_points.txt
pyseek-0.2.1.dist-info/WHEEL
pyseek-0.2.1.dist-info/METADATA
pyseek-0.2.1.dist-info/RECORD
