Metadata-Version: 2.1
Name: pyseek
Version: 0.2.1
Summary: A command line tool for accessing the SEC EDGAR database.
Author: Zach Lopez
Author-email: zachlopez9@gmail.com
Requires-Python: >=3.9,<4.0
Classifier: Programming Language :: Python :: 3
Classifier: Programming Language :: Python :: 3.9
Classifier: Programming Language :: Python :: 3.10
Classifier: Programming Language :: Python :: 3.11
Requires-Dist: black (>=23.1.0,<24.0.0)
Requires-Dist: requests (>=2.28.2,<3.0.0)
Requires-Dist: typer[all] (>=0.7.0,<0.8.0)
